Metadata-Version: 1.0
Name: pyaeries
Version: 1.0
Summary: Aeries SIS API
Home-page: UNKNOWN
Author: Jeff Tchang
Author-email: jeff.tchang@gmail.com
License: UNKNOWN
Keywords: aeries api
Platform: UNKNOWN
